etdd
