Metadata-Version: 2.1
Name: etdd
Version: 0.0.8
Summary: eTDD framework
Home-page: https://github.com/neubertm/TDD_framework
Author: Milan Neubert, Felipe Bombardelli
Author-email: felipebombardelli@gmail.com
License: UNKNOWN
Platform: UNKNOWN
Classifier: Programming Language :: Python :: 3
Classifier: Programming Language :: Python :: 3.7
Classifier: Programming Language :: Python :: 3.8
Classifier: Topic :: Software Development :: Libraries :: Python Modules
Classifier: License :: OSI Approved :: MIT License
Classifier: Operating System :: OS Independent
Requires-Python: >=3
License-File: LICENSE
